arrow_bcp/__init__.py
arrow_bcp/bcp_con.py
arrow_bcp/bcp_data.py
arrow_bcp/bcp_format.py
arrow_bcp/zig_ext.abi3.so
arrow_bcp-0.9.3.dist-info/METADATA
arrow_bcp-0.9.3.dist-info/WHEEL
arrow_bcp-0.9.3.dist-info/top_level.txt
arrow_bcp-0.9.3.dist-info/RECORD
arrow_bcp-0.9.3.dist-info/licenses/LICENSE
