Metadata-Version: 2.4
Name: arrow-bcp
Version: 0.9.3
Summary: Transfer data between pyarrow and SQL Server using Microsoft's Bulk Copy Program
Author: Felix Graßl
License-Expression: MIT
Project-URL: Homepage, https://github.com/ffelixg/arrow_bcp
Project-URL: Issues, https://github.com/ffelixg/arrow_bcp/issues
Keywords: bcp,arrow,mssql,sql server
Classifier: Programming Language :: Python
Classifier: Topic :: Database
Classifier: Intended Audience :: Developers
Requires-Python: >=3.10
License-File: LICENSE
Requires-Dist: pyarrow
Dynamic: license-file
